CHANGES.txt
LICENSE.txt
MANIFEST.in
README.md
pyproject.toml
setup.cfg
setup.py
tox.ini
src/opengraph_writer/__init__.py
src/opengraph_writer/py.typed
src/opengraph_writer/pyramid_helpers.py
src/opengraph_writer.egg-info/PKG-INFO
src/opengraph_writer.egg-info/SOURCES.txt
src/opengraph_writer.egg-info/dependency_links.txt
src/opengraph_writer.egg-info/not-zip-safe
src/opengraph_writer.egg-info/requires.txt
src/opengraph_writer.egg-info/top_level.txt
tests/__init__.py
tests/test_core.py
tests/test_pyramid_integration.py