Metadata-Version: 2.1
Name: opengraph-writer
Version: 0.4.0
Summary: Lightweight OpenGraph support for writing and validating objects.
Home-page: https://github.com/jvanasco/opengraph_writer
Author: Jonathan Vanasco
Author-email: jonathan@findmeon.com
License: MIT
Keywords: facebook opengraph open graph web pyramid
Classifier: Intended Audience :: Developers
Classifier: Framework :: Pyramid
Classifier: Programming Language :: Python :: 3
Classifier: Programming Language :: Python :: 3.6
Classifier: Programming Language :: Python :: 3.7
Classifier: Programming Language :: Python :: 3.8
Classifier: Programming Language :: Python :: 3.9
Classifier: Programming Language :: Python :: 3.10
Classifier: Programming Language :: Python :: 3.11
Classifier: License :: OSI Approved :: MIT License
Requires-Python: >=3.6
Provides-Extra: testing
License-File: LICENSE.txt
